CMakeLists.txt
LICENSE.md
MANIFEST.in
README.md
setup.py
cpp/CMakeLists.txt
cpp/kitetools/CMakeLists.txt
cpp/kitetools/include/ComplexTraits.hpp
cpp/kitetools/include/arpes.hpp
cpp/kitetools/include/calculate.hpp
cpp/kitetools/include/compiletime_info.hpp
cpp/kitetools/include/conductivity_optical.hpp
cpp/kitetools/include/dos.hpp
cpp/kitetools/include/functions.hpp
cpp/kitetools/include/ldos.hpp
cpp/kitetools/include/macros.hpp
cpp/kitetools/include/messages.hpp
cpp/kitetools/include/myHDF5.hpp
cpp/kitetools/include/parse_input.hpp
cpp/kitetools/include/systemInfo.hpp
cpp/kitetools/include/cond_2order/Gamma0.hpp
cpp/kitetools/include/cond_2order/Gamma0photo.hpp
cpp/kitetools/include/cond_2order/Gamma1.hpp
cpp/kitetools/include/cond_2order/Gamma1photo.hpp
cpp/kitetools/include/cond_2order/Gamma2.hpp
cpp/kitetools/include/cond_2order/Gamma2photo.hpp
cpp/kitetools/include/cond_2order/Gamma3.hpp
cpp/kitetools/include/cond_2order/Gamma3photo.hpp
cpp/kitetools/include/cond_2order/conductivity_2order.hpp
cpp/kitetools/include/cond_dc/conductivity_dc.hpp
cpp/kitetools/src/arpes.cpp
cpp/kitetools/src/calculate.cpp
cpp/kitetools/src/compiletime_info.h.in
cpp/kitetools/src/conductivity_optical.cpp
cpp/kitetools/src/dos.cpp
cpp/kitetools/src/functions.cpp
cpp/kitetools/src/ldos.cpp
cpp/kitetools/src/main.cpp
cpp/kitetools/src/myHDF5.cpp
cpp/kitetools/src/parse_input.cpp
cpp/kitetools/src/systemInfo.cpp
cpp/kitetools/src/cond_2order/Gamma0.cpp
cpp/kitetools/src/cond_2order/Gamma0photo.cpp
cpp/kitetools/src/cond_2order/Gamma1.cpp
cpp/kitetools/src/cond_2order/Gamma1photo.cpp
cpp/kitetools/src/cond_2order/Gamma2.cpp
cpp/kitetools/src/cond_2order/Gamma2photo.cpp
cpp/kitetools/src/cond_2order/Gamma3.cpp
cpp/kitetools/src/cond_2order/Gamma3photo.cpp
cpp/kitetools/src/cond_2order/conductivity_2order.cpp
cpp/kitetools/src/cond_dc/conductivity_dc.cpp
cpp/kitetools/src/cond_dc/fill.cpp
cpp/kitex/CMakeLists.txt
cpp/kitex/include/ComplexTraits.hpp
cpp/kitex/include/Coordinates.hpp
quantum_kite_MAndelkovic.egg-info/PKG-INFO
quantum_kite_MAndelkovic.egg-info/SOURCES.txt
quantum_kite_MAndelkovic.egg-info/dependency_links.txt
quantum_kite_MAndelkovic.egg-info/not-zip-safe
quantum_kite_MAndelkovic.egg-info/requires.txt
quantum_kite_MAndelkovic.egg-info/top_level.txt
