Metadata-Version: 1.0
Name: quantum-kite-MAndelkovic
Version: 2.0.3
Summary: A test KITE project using pybind11 and CMake
Home-page: UNKNOWN
Author: Misa
Author-email: misa.s.andelkovic@gmail.com
License: UNKNOWN
Platform: UNKNOWN
